{
  "date": "2026-05-01",
  "timestamp": "2026-05-01T19:01:39.077194Z",
  "system": "TENVARIS INQDATA Engine v1.0.0",
  "signal": {
    "FDRI": 0.4043,
    "F_t": 0.3851,
    "regime": "Systemic",
    "signal": "ACT",
    "A_t": 1.358,
    "collar": "moderate",
    "calc_hash": "2c42413c4681",
    "L_t": 0.3605,
    "V_t": 0.462,
    "C_t": 0.398,
    "Q_t": 0.1654,
    "LCRI_t": 0.3678,
    "p_stable": 0.0,
    "p_stress": 0.7278
  },
  "trade_recommendation": {
    "core_action": "LONG SPY \u2014 REDUCED 50%",
    "core_instrument": "SPY @ ~$721.11",
    "hedge_type": "LONG STRADDLE + ELEVATED VOL",
    "put_instrument": "SPY Put $671",
    "put_strike_pct": -7.0,
    "put_expiry": "2026-06-19",
    "call_instrument": "SPY ATM Call $721",
    "payoff_up": 4.5,
    "payoff_down": 4.5,
    "max_loss": 1.8,
    "rec_hash": "7d24f9210198"
  },
  "derivatives": {
    "vix_spot": 17.010000228881836,
    "vix_3m": 20.239999771118164,
    "skew": 143.3300018310547,
    "vvix": 94.30000305175781,
    "term_structure": "CONTANGO",
    "stress_level": "ELEVATED",
    "aggregate_score": 0.475
  },
  "audit": {
    "immutable": true,
    "chain_hash": "2c42413c4681",
    "note": "Signal generated before market open. Cannot be retroactively modified."
  }
}